{
  "kind": "collectionType",
  "collectionName": "projects",
  "info": {
    "singularName": "project",
    "pluralName": "projects",
    "displayName": "Project",
    "description": ""
  },
  "options": {
    "draftAndPublish": true
  },
  "pluginOptions": {},
  "attributes": {
    "title": {
      "type": "string",
      "required": true
    },
    "cover": {
      "type": "media",
      "multiple": false,
      "required": true,
      "allowedTypes": [
        "images"
      ]
    },
    "technologies": {
      "type": "media",
      "multiple": true,
      "required": true,
      "allowedTypes": [
        "images"
      ]
    },
    "siteURL": {
      "type": "string",
      "required": true
    },
    "repoURL": {
      "type": "string",
      "required": false
    },
    "slug": {
      "type": "uid",
      "targetField": "title"
    },
    "description": {
      "type": "blocks"
    },
    "client": {
      "type": "string",
      "required": true
    }
  }
}
